setup.py
src/Hatak_DebugToolBar.egg-info/PKG-INFO
src/Hatak_DebugToolBar.egg-info/SOURCES.txt
src/Hatak_DebugToolBar.egg-info/dependency_links.txt
src/Hatak_DebugToolBar.egg-info/namespace_packages.txt
src/Hatak_DebugToolBar.egg-info/not-zip-safe
src/Hatak_DebugToolBar.egg-info/requires.txt
src/Hatak_DebugToolBar.egg-info/top_level.txt
src/haplugin/__init__.py
src/haplugin/debugtoolbar.py