Metadata-Version: 1.0
Name: Hatak-DebugToolBar
Version: 0.1
Summary: Debug Tool Bar plugin for Hatak.
Home-page: UNKNOWN
Author: UNKNOWN
Author-email: UNKNOWN
License: Apache License 2.0
Platform: UNKNOWN
